AUTHORS.rst
CHANGES.rst
LICENSE.txt
MANIFEST.in
README.rst
TODO.rst
setup.py
django_jstemplate.egg-info/PKG-INFO
django_jstemplate.egg-info/SOURCES.txt
django_jstemplate.egg-info/dependency_links.txt
django_jstemplate.egg-info/not-zip-safe
django_jstemplate.egg-info/requires.txt
django_jstemplate.egg-info/top_level.txt
jstemplate/__init__.py
jstemplate/conf.py
jstemplate/finders.py
jstemplate/loading.py
jstemplate/models.py
jstemplate/preprocessors.py
jstemplate/management/__init__.py
jstemplate/management/commands/__init__.py
jstemplate/management/commands/makemessages.py
jstemplate/static/libs/django.mustache.js
jstemplate/templatetags/__init__.py
jstemplate/templatetags/base.py
jstemplate/templatetags/dustjs.py
jstemplate/templatetags/handlebarsjs.py
jstemplate/templatetags/icanhazjs.py
jstemplate/templatetags/jstemplate.py
jstemplate/templatetags/mustachejs.py
jstemplate/templatetags/rawjstemplate.py
jstemplate/tests/__init__.py
jstemplate/tests/mockfinders.py
jstemplate/tests/mockpreprocessors.py
jstemplate/tests/test_finders.py
jstemplate/tests/test_loading.py
jstemplate/tests/test_makemessages.py
jstemplate/tests/test_translation.py
jstemplate/tests/test_ttag.py