Metadata-Version: 2.1
Name: django-jstemplate
Version: 2.0.1
Summary: A Django template tag for embedding Mustache.js templates -- or other JavaScript templates -- safely.
Home-page: https://github.com/mjumbewu/django-jstemplate/
Author: Mjumbe Wawatu Ukweli
Author-email: mjumbewu@gmail.com
License: UNKNOWN
Platform: UNKNOWN
Classifier: Development Status :: 4 - Beta
Classifier: Environment :: Web Environment
Classifier: Intended Audience :: Developers
Classifier: License :: OSI Approved :: BSD License
Classifier: Operating System :: OS Independent
Classifier: Programming Language :: Python
Classifier: Programming Language :: Python :: 3
Classifier: Programming Language :: Python :: 3.7
Classifier: Programming Language :: Python :: 3.8
Classifier: Programming Language :: Python :: 3.9
Classifier: Programming Language :: Python :: 3.10
Classifier: Framework :: Django
License-File: LICENSE.txt
License-File: AUTHORS.rst
